{
    "3": {
        "Date of creation": "2023-04-14T17:27:15.591041",
        "Date of editing": "2023-04-14T17:27:15.591041",
        "Caption": "3",
        "Text": "3"
    },
    "0": {
        "Date of creation": "2023-04-14T17:18:58.588712",
        "Date of editing": "2023-04-14T17:27:24.083924",
        "Caption": "0",
        "Text": "0"
    },
    "1": {
        "Date of creation": "2023-04-14T17:19:01.348360",
        "Date of editing": "2023-04-14T17:29:04.122531",
        "Caption": "1",
        "Text": "1"
    }
}